nrt/__init__.py
nrt/nrt.py
nrt/rapc/__init__.py
nrt/rapc/rapc.py
nrt/rapc/rapc_templates/CMakeLists_template.txt
nrt/rapc/rapc_templates/header_template.hpp
nrt/rapc/rapc_templates/src_template.cpp
nexte_ros2_tool-0.1.3.dist-info/METADATA
nexte_ros2_tool-0.1.3.dist-info/WHEEL
nexte_ros2_tool-0.1.3.dist-info/entry_points.txt
nexte_ros2_tool-0.1.3.dist-info/top_level.txt
nexte_ros2_tool-0.1.3.dist-info/RECORD
