Metadata-Version: 2.4
Name: nexte-ros2-tool
Version: 0.1.3
Summary: NEXT E ros2 tools
Author-email: ZiYu <ziyedeyuu@163.com>
License: MIT
Keywords: cli,ros2,NEXT E
Requires-Python: >=3.8
Requires-Dist: argparse
